{"uploader_id": "collegehumor", "playlist_index": null, "like_count": 16616, "format_id": "22", "dislike_count": 3855, "ext": "mp4", "playlist": null, "id": "69ewVbNIvvI", "display_id": "69ewVbNIvvI", "title": "I'm Not Awake (Katy Perry Parody)", "extractor": "youtube", "extractor_key": "Youtube", "thumbnail": "https://i1.ytimg.com/vi/69ewVbNIvvI/maxresdefault.jpg", "view_count": 1869372, "width": 1280, "fulltitle": "I'm Not Awake (Katy Perry Parody)", "player_url": null, "description": "CH Bonus Footage http://bit.ly/Nm10EI\nLIKE us on: http://www.facebook.com/collegehumor\n\nShe feels like she's living a teenage dream.\n\nSee more http://www.collegehumor.com\nFOLLOW us on: http://www.twitter.com/collegehumor\nFOLLOW us on: http://www.collegehumor.tumblr.com", "format": "22 - 1280x720", "url": "https://r17---sn-tt17dn7y.googlevideo.com/videoplayback?itag=22&key=yt5&source=youtube&pcm2fr=yes&sver=3&expire=1397226430&ipbits=0&ratebypass=yes&ip=18.111.47.22&upn=b6OaQmHTGMU&signature=DBF56A3E7E9F59245762CD356D82893DC2B92DFC.1B848A066781F67317FF3CE92AB1B0C5443E66E0&requiressl=yes&sparams=id%2Cip%2Cipbits%2Citag%2Cpcm2fr%2Cratebypass%2Crequiressl%2Csource%2Cupn%2Cexpire&id=o-ADTGuwY5VCdZWU5sM9jgF-LAK6IFJYlfREIxGgz4twaS&mv=m&mt=1397202035&fexp=919127%2C931919%2C945014%2C916807%2C914060%2C916623%2C937417%2C913434%2C936916%2C934022%2C936923&ms=au", "uploader": "CollegeHumor", "webpage_url": "https://www.youtube.com/watch?v=69ewVbNIvvI", "stitle": "I'm Not Awake (Katy Perry Parody)", "webpage_url_basename": "watch", "height": 720, "formats": [{"format": "171 - audio only (DASH webm audio)", "format_id": "171", "vcodec": "none", "ext": "webm", "player_url": null, "format_note": "DASH webm audio", "abr": 48, "url": "https://r17---sn-tt17dn7y.googlevideo.com/videoplayback?itag=171&key=yt5&source=youtube&clen=2472599&sver=3&expire=1397226430&ipbits=0&upn=-eKkbge-fW8&gir=yes&ms=au&signature=45F47705FD8D1341EE7584E33A498F60CFC99BF7.4F451763A8A8E4744FFE464A5C13111DE875C91A&pcm2fr=yes&lmt=1393673389020618&requiressl=yes&dur=167.008&id=o-ADTGuwY5VCdZWU5sM9jgF-LAK6IFJYlfREIxGgz4twaS&mv=m&ip=18.111.47.22&fexp=919127%2C931919%2C945014%2C916807%2C914060%2C916623%2C937417%2C913434%2C936916%2C934022%2C936923&mt=1397202035&sparams=clen%2Cdur%2Cgir%2Cid%2Cip%2Cipbits%2Citag%2Clmt%2Cpcm2fr%2Crequiressl%2Csource%2Cupn%2Cexpire&ratebypass=yes", "preference": -50}, {"format": "140 - audio only (DASH audio)", "format_id": "140", "vcodec": "none", "ext": "m4a", "player_url": null, "format_note": "DASH audio", "abr": 128, "url": "https://r17---sn-tt17dn7y.googlevideo.com/videoplayback?itag=140&key=yt5&source=youtube&clen=2654024&sver=3&expire=1397226430&ipbits=0&upn=-eKkbge-fW8&gir=yes&ms=au&signature=88DBCAB513C2EA65781986D02115C504E7A221D1.4F328B764CA63749569E2004ECD14E6B37C30345&pcm2fr=yes&lmt=1394266395961842&requiressl=yes&dur=167.067&id=o-ADTGuwY5VCdZWU5sM9jgF-LAK6IFJYlfREIxGgz4twaS&mv=m&ip=18.111.47.22&fexp=919127%2C931919%2C945014%2C916807%2C914060%2C916623%2C937417%2C913434%2C936916%2C934022%2C936923&mt=1397202035&sparams=clen%2Cdur%2Cgir%2Cid%2Cip%2Cipbits%2Citag%2Clmt%2Cpcm2fr%2Crequiressl%2Csource%2Cupn%2Cexpire&ratebypass=yes", "preference": -50}, {"format": "160 - 144p (DASH video)", "format_id": "160", "ext": "mp4", "player_url": null, "format_note": "DASH video", "height": 144, "url": "https://r17---sn-tt17dn7y.googlevideo.com/videoplayback?itag=160&key=yt5&source=youtube&clen=2338401&sver=3&expire=1397226430&ipbits=0&upn=-eKkbge-fW8&gir=yes&ms=au&signature=59762A9E60D2EFE964334C98D16BC576B32D8B3D.A0BBDA8E1EC58F22EF51C20C4F50C0A3B3BE1C63&pcm2fr=yes&lmt=1394266381606129&requiressl=yes&dur=166.959&id=o-ADTGuwY5VCdZWU5sM9jgF-LAK6IFJYlfREIxGgz4twaS&mv=m&ip=18.111.47.22&fexp=919127%2C931919%2C945014%2C916807%2C914060%2C916623%2C937417%2C913434%2C936916%2C934022%2C936923&mt=1397202035&sparams=clen%2Cdur%2Cgir%2Cid%2Cip%2Cipbits%2Citag%2Clmt%2Cpcm2fr%2Crequiressl%2Csource%2Cupn%2Cexpire&ratebypass=yes", "preference": -40, "acodec": "none"}, {"player_url": null, "format_note": "DASH webm", "height": 240, "format": "242 - 240p (DASH webm)", "format_id": "242", "ext": "webm", "url": "https://r17---sn-tt17dn7y.googlevideo.com/videoplayback?itag=242&key=yt5&source=youtube&clen=3392370&sver=3&expire=1397226430&ipbits=0&upn=-eKkbge-fW8&gir=yes&ms=au&signature=BF52BB8CE63299EBA940437E8D0AE27F86BA68AC.867CD3B7B5F861C34C3C2AE7E773EFDE3D4B9189&pcm2fr=yes&lmt=1393673575885297&requiressl=yes&dur=166.958&id=o-ADTGuwY5VCdZWU5sM9jgF-LAK6IFJYlfREIxGgz4twaS&mv=m&ip=18.111.47.22&fexp=919127%2C931919%2C945014%2C916807%2C914060%2C916623%2C937417%2C913434%2C936916%2C934022%2C936923&mt=1397202035&sparams=clen%2Cdur%2Cgir%2Cid%2Cip%2Cipbits%2Citag%2Clmt%2Cpcm2fr%2Crequiressl%2Csource%2Cupn%2Cexpire&ratebypass=yes", "preference": -40}, {"format": "133 - 240p (DASH video)", "format_id": "133", "ext": "mp4", "player_url": null, "format_note": "DASH video", "height": 240, "url": "https://r17---sn-tt17dn7y.googlevideo.com/videoplayback?itag=133&key=yt5&source=youtube&clen=5129147&sver=3&expire=1397226430&ipbits=0&upn=-eKkbge-fW8&gir=yes&ms=au&signature=60A5DDC9BC4E9419EF7C03E3ED920A2D8EE6DEFE.F0437213DCD80A94977EFEE75212A8CA2315BBFD&pcm2fr=yes&lmt=1394266382539642&requiressl=yes&dur=166.959&id=o-ADTGuwY5VCdZWU5sM9jgF-LAK6IFJYlfREIxGgz4twaS&mv=m&ip=18.111.47.22&fexp=919127%2C931919%2C945014%2C916807%2C914060%2C916623%2C937417%2C913434%2C936916%2C934022%2C936923&mt=1397202035&sparams=clen%2Cdur%2Cgir%2Cid%2Cip%2Cipbits%2Citag%2Clmt%2Cpcm2fr%2Crequiressl%2Csource%2Cupn%2Cexpire&ratebypass=yes", "preference": -40, "acodec": "none"}, {"player_url": null, "format_note": "DASH webm", "height": 360, "format": "243 - 360p (DASH webm)", "format_id": "243", "ext": "webm", "url": "https://r17---sn-tt17dn7y.googlevideo.com/videoplayback?itag=243&key=yt5&source=youtube&clen=6191387&sver=3&expire=1397226430&ipbits=0&upn=-eKkbge-fW8&gir=yes&ms=au&signature=6F938686A3D27CA01038CE61973193889B0C59D4.C6A808CBE6D4138C5580F5957D855FB5FD10A988&pcm2fr=yes&lmt=1393673574160447&requiressl=yes&dur=166.958&id=o-ADTGuwY5VCdZWU5sM9jgF-LAK6IFJYlfREIxGgz4twaS&mv=m&ip=18.111.47.22&fexp=919127%2C931919%2C945014%2C916807%2C914060%2C916623%2C937417%2C913434%2C936916%2C934022%2C936923&mt=1397202035&sparams=clen%2Cdur%2Cgir%2Cid%2Cip%2Cipbits%2Citag%2Clmt%2Cpcm2fr%2Crequiressl%2Csource%2Cupn%2Cexpire&ratebypass=yes", "preference": -40}, {"format": "134 - 360p (DASH video)", "format_id": "134", "ext": "mp4", "player_url": null, "format_note": "DASH video", "height": 360, "url": "https://r17---sn-tt17dn7y.googlevideo.com/videoplayback?itag=134&key=yt5&source=youtube&clen=6567305&sver=3&expire=1397226430&ipbits=0&upn=-eKkbge-fW8&gir=yes&ms=au&signature=69F3ECADF8BEEC65B0CCCD3DDD057A744E01960E.30FA80F49427A233999056C23B29D92972F939&pcm2fr=yes&lmt=1394266387367331&requiressl=yes&dur=166.959&id=o-ADTGuwY5VCdZWU5sM9jgF-LAK6IFJYlfREIxGgz4twaS&mv=m&ip=18.111.47.22&fexp=919127%2C931919%2C945014%2C916807%2C914060%2C916623%2C937417%2C913434%2C936916%2C934022%2C936923&mt=1397202035&sparams=clen%2Cdur%2Cgir%2Cid%2Cip%2Cipbits%2Citag%2Clmt%2Cpcm2fr%2Crequiressl%2Csource%2Cupn%2Cexpire&ratebypass=yes", "preference": -40, "acodec": "none"}, {"player_url": null, "format_note": "DASH webm", "height": 480, "format": "244 - 480p (DASH webm)", "format_id": "244", "ext": "webm", "url": "https://r17---sn-tt17dn7y.googlevideo.com/videoplayback?itag=244&key=yt5&source=youtube&clen=11286066&sver=3&expire=1397226430&ipbits=0&upn=-eKkbge-fW8&gir=yes&ms=au&signature=5FD73D0AB3C7C8D4D7EDCB4248D906B8B3D20CAC.EB7D5300FE68011297B76A76C76B4955BB2A1B95&pcm2fr=yes&lmt=1393673577258821&requiressl=yes&dur=166.958&id=o-ADTGuwY5VCdZWU5sM9jgF-LAK6IFJYlfREIxGgz4twaS&mv=m&ip=18.111.47.22&fexp=919127%2C931919%2C945014%2C916807%2C914060%2C916623%2C937417%2C913434%2C936916%2C934022%2C936923&mt=1397202035&sparams=clen%2Cdur%2Cgir%2Cid%2Cip%2Cipbits%2Citag%2Clmt%2Cpcm2fr%2Crequiressl%2Csource%2Cupn%2Cexpire&ratebypass=yes", "preference": -40}, {"format": "135 - 480p (DASH video)", "format_id": "135", "ext": "mp4", "player_url": null, "format_note": "DASH video", "height": 480, "url": "https://r17---sn-tt17dn7y.googlevideo.com/videoplayback?itag=135&key=yt5&source=youtube&clen=12435140&sver=3&expire=1397226430&ipbits=0&upn=-eKkbge-fW8&gir=yes&ms=au&signature=727E7970F98E3C0C68A041DE46E2E9A56AFC7145.D574F70C26EB1C1BA1207532B8F096EBB7E7A460&pcm2fr=yes&lmt=1394266391400049&requiressl=yes&dur=166.959&id=o-ADTGuwY5VCdZWU5sM9jgF-LAK6IFJYlfREIxGgz4twaS&mv=m&ip=18.111.47.22&fexp=919127%2C931919%2C945014%2C916807%2C914060%2C916623%2C937417%2C913434%2C936916%2C934022%2C936923&mt=1397202035&sparams=clen%2Cdur%2Cgir%2Cid%2Cip%2Cipbits%2Citag%2Clmt%2Cpcm2fr%2Crequiressl%2Csource%2Cupn%2Cexpire&ratebypass=yes", "preference": -40, "acodec": "none"}, {"player_url": null, "format_note": "DASH webm", "height": 720, "format": "247 - 720p (DASH webm)", "format_id": "247", "ext": "webm", "url": "https://r17---sn-tt17dn7y.googlevideo.com/videoplayback?itag=247&key=yt5&source=youtube&clen=21194512&sver=3&expire=1397226430&ipbits=0&upn=-eKkbge-fW8&gir=yes&ms=au&signature=515A0C6F91F01F02C656D174449B6FD69D0D9C6B.153950D3FC60B22126E2EAE0C2572E961D2FC109&pcm2fr=yes&lmt=1393684354641995&requiressl=yes&dur=166.958&id=o-ADTGuwY5VCdZWU5sM9jgF-LAK6IFJYlfREIxGgz4twaS&mv=m&ip=18.111.47.22&fexp=919127%2C931919%2C945014%2C916807%2C914060%2C916623%2C937417%2C913434%2C936916%2C934022%2C936923&mt=1397202035&sparams=clen%2Cdur%2Cgir%2Cid%2Cip%2Cipbits%2Citag%2Clmt%2Cpcm2fr%2Crequiressl%2Csource%2Cupn%2Cexpire&ratebypass=yes", "preference": -40}, {"format": "136 - 720p (DASH video)", "format_id": "136", "ext": "mp4", "player_url": null, "format_note": "DASH video", "height": 720, "url": "https://r17---sn-tt17dn7y.googlevideo.com/videoplayback?itag=136&key=yt5&source=youtube&clen=25579907&sver=3&expire=1397226430&ipbits=0&upn=-eKkbge-fW8&gir=yes&ms=au&signature=01746A84DB36CF3F8BD533C3069591F31D4C915F.D66E91A62237CC4D1090BD2966D109571C2A938C&pcm2fr=yes&lmt=1394266485857415&requiressl=yes&dur=166.959&id=o-ADTGuwY5VCdZWU5sM9jgF-LAK6IFJYlfREIxGgz4twaS&mv=m&ip=18.111.47.22&fexp=919127%2C931919%2C945014%2C916807%2C914060%2C916623%2C937417%2C913434%2C936916%2C934022%2C936923&mt=1397202035&sparams=clen%2Cdur%2Cgir%2Cid%2Cip%2Cipbits%2Citag%2Clmt%2Cpcm2fr%2Crequiressl%2Csource%2Cupn%2Cexpire&ratebypass=yes", "preference": -40, "acodec": "none"}, {"player_url": null, "height": 144, "format": "17 - 176x144", "format_id": "17", "ext": "3gp", "url": "https://r17---sn-tt17dn7y.googlevideo.com/videoplayback?itag=17&key=yt5&source=youtube&pcm2fr=yes&sver=3&expire=1397226430&ipbits=0&upn=b6OaQmHTGMU&ip=18.111.47.22&signature=509B8316C89750F138FF494305076180268EDA33.9D0093BA112868A6E4B1419855BB274C4A22DF1F&requiressl=yes&sparams=id%2Cip%2Cipbits%2Citag%2Cpcm2fr%2Crequiressl%2Csource%2Cupn%2Cexpire&id=o-ADTGuwY5VCdZWU5sM9jgF-LAK6IFJYlfREIxGgz4twaS&mv=m&mt=1397202035&fexp=919127%2C931919%2C945014%2C916807%2C914060%2C916623%2C937417%2C913434%2C936916%2C934022%2C936923&ms=au&ratebypass=yes", "width": 176}, {"player_url": null, "height": 240, "format": "36 - 320x240", "format_id": "36", "ext": "3gp", "url": "https://r17---sn-tt17dn7y.googlevideo.com/videoplayback?itag=36&key=yt5&source=youtube&pcm2fr=yes&sver=3&expire=1397226430&ipbits=0&upn=b6OaQmHTGMU&ip=18.111.47.22&signature=12E2F7BCB2299910EB2DEEF9A2040AC45ADFEA63.481C46AFED51697BDA53548A1553ED3500A059F3&requiressl=yes&sparams=id%2Cip%2Cipbits%2Citag%2Cpcm2fr%2Crequiressl%2Csource%2Cupn%2Cexpire&id=o-ADTGuwY5VCdZWU5sM9jgF-LAK6IFJYlfREIxGgz4twaS&mv=m&mt=1397202035&fexp=919127%2C931919%2C945014%2C916807%2C914060%2C916623%2C937417%2C913434%2C936916%2C934022%2C936923&ms=au&ratebypass=yes", "width": 320}, {"player_url": null, "height": 240, "format": "5 - 400x240", "format_id": "5", "ext": "flv", "url": "https://r17---sn-tt17dn7y.googlevideo.com/videoplayback?itag=5&key=yt5&source=youtube&pcm2fr=yes&sver=3&expire=1397226430&ipbits=0&upn=b6OaQmHTGMU&ip=18.111.47.22&signature=B0A690DB0430676C65171C810FE3491C0FF2EAEC.6B43BDB9B26A0521909EEA44295D022F29DFACFB&requiressl=yes&sparams=id%2Cip%2Cipbits%2Citag%2Cpcm2fr%2Crequiressl%2Csource%2Cupn%2Cexpire&id=o-ADTGuwY5VCdZWU5sM9jgF-LAK6IFJYlfREIxGgz4twaS&mv=m&mt=1397202035&fexp=919127%2C931919%2C945014%2C916807%2C914060%2C916623%2C937417%2C913434%2C936916%2C934022%2C936923&ms=au&ratebypass=yes", "width": 400}, {"player_url": null, "height": 360, "format": "43 - 640x360", "format_id": "43", "ext": "webm", "url": "https://r17---sn-tt17dn7y.googlevideo.com/videoplayback?itag=43&key=yt5&source=youtube&pcm2fr=yes&sver=3&expire=1397226430&ipbits=0&ratebypass=yes&ip=18.111.47.22&upn=b6OaQmHTGMU&signature=34BD0F30C4952AAB8B5208A20AFAD3D82A760DDD.2D4CA01681E0C8DCADC2FB421AF547E742517946&requiressl=yes&sparams=id%2Cip%2Cipbits%2Citag%2Cpcm2fr%2Cratebypass%2Crequiressl%2Csource%2Cupn%2Cexpire&id=o-ADTGuwY5VCdZWU5sM9jgF-LAK6IFJYlfREIxGgz4twaS&mv=m&mt=1397202035&fexp=919127%2C931919%2C945014%2C916807%2C914060%2C916623%2C937417%2C913434%2C936916%2C934022%2C936923&ms=au", "width": 640}, {"player_url": null, "height": 360, "format": "18 - 640x360", "format_id": "18", "ext": "mp4", "url": "https://r17---sn-tt17dn7y.googlevideo.com/videoplayback?itag=18&key=yt5&source=youtube&pcm2fr=yes&sver=3&expire=1397226430&ipbits=0&ratebypass=yes&ip=18.111.47.22&upn=b6OaQmHTGMU&signature=6F4E3414A194CED11C86EAEE3EDC58D602E5A283.BA6875EDD94DCF0A3159A8CD274084BC2ECC3C99&requiressl=yes&sparams=id%2Cip%2Cipbits%2Citag%2Cpcm2fr%2Cratebypass%2Crequiressl%2Csource%2Cupn%2Cexpire&id=o-ADTGuwY5VCdZWU5sM9jgF-LAK6IFJYlfREIxGgz4twaS&mv=m&mt=1397202035&fexp=919127%2C931919%2C945014%2C916807%2C914060%2C916623%2C937417%2C913434%2C936916%2C934022%2C936923&ms=au", "width": 640}, {"player_url": null, "height": 720, "format": "22 - 1280x720", "format_id": "22", "ext": "mp4", "url": "https://r17---sn-tt17dn7y.googlevideo.com/videoplayback?itag=22&key=yt5&source=youtube&pcm2fr=yes&sver=3&expire=1397226430&ipbits=0&ratebypass=yes&ip=18.111.47.22&upn=b6OaQmHTGMU&signature=DBF56A3E7E9F59245762CD356D82893DC2B92DFC.1B848A066781F67317FF3CE92AB1B0C5443E66E0&requiressl=yes&sparams=id%2Cip%2Cipbits%2Citag%2Cpcm2fr%2Cratebypass%2Crequiressl%2Csource%2Cupn%2Cexpire&id=o-ADTGuwY5VCdZWU5sM9jgF-LAK6IFJYlfREIxGgz4twaS&mv=m&mt=1397202035&fexp=919127%2C931919%2C945014%2C916807%2C914060%2C916623%2C937417%2C913434%2C936916%2C934022%2C936923&ms=au", "width": 1280}], "annotations": null, "duration": 168, "age_limit": 0, "upload_date": "20121105", "subtitles": null}