{"format": "18 - 640x360", "stitle": "Marilyn Manson And The Spooky Kids - Herpes [coke and sodomy version]", "extractor_key": "Youtube", "formats": [{"ext": "m4a", "url": "https://r3---sn-a8au-cvne.googlevideo.com/videoplayback?sparams=clen%2Cdur%2Cgir%2Cid%2Cip%2Cipbits%2Citag%2Clmt%2Crequiressl%2Csource%2Cupn%2Cexpire&key=yt5&itag=140&source=youtube&ms=au&fexp=931945%2C937417%2C913434%2C936916%2C934022%2C936923&mws=yes&ip=18.111.47.22&expire=1397255826&upn=GvZMjhbNN_M&ipbits=0&dur=579.291&requiressl=yes&mv=m&id=o-AOrBy4nOUh9_ykTNecZuCOtqwZEhyc23uMWiMM8L8xdt&sver=3&clen=9200938&gir=yes&lmt=1379262889154126&mt=1397234678&signature=3B8357B4E3E5074D81127904CC0B82A74B8D12BE.39B7B7EE770D44CFC85F89C16AA337AF9474852F&ratebypass=yes", "preference": -50, "vcodec": "none", "abr": 128, "player_url": "//s.ytimg.com/yts/jsbin/html5player-en_US-vflS6PgfC.js", "format_id": "140", "format_note": "DASH audio", "format": "140 - audio only (DASH audio)"}, {"ext": "mp4", "acodec": "none", "url": "https://r3---sn-a8au-cvne.googlevideo.com/videoplayback?sparams=clen%2Cdur%2Cgir%2Cid%2Cip%2Cipbits%2Citag%2Clmt%2Crequiressl%2Csource%2Cupn%2Cexpire&key=yt5&itag=160&source=youtube&ms=au&fexp=931945%2C937417%2C913434%2C936916%2C934022%2C936923&mws=yes&ip=18.111.47.22&expire=1397255826&upn=GvZMjhbNN_M&ipbits=0&dur=576.300&requiressl=yes&mv=m&id=o-AOrBy4nOUh9_ykTNecZuCOtqwZEhyc23uMWiMM8L8xdt&sver=3&clen=3438267&gir=yes&lmt=1379262895927732&mt=1397234678&signature=07EF5CB69FB397B1EE99A91E963694C107D119EC.749AE454752CBA907044A97E1B6489FD4BEE666B&ratebypass=yes", "preference": -40, "height": 144, "player_url": "//s.ytimg.com/yts/jsbin/html5player-en_US-vflS6PgfC.js", "format_id": "160", "format_note": "DASH video", "format": "160 - 144p (DASH video)"}, {"ext": "mp4", "acodec": "none", "url": "https://r3---sn-a8au-cvne.googlevideo.com/videoplayback?sparams=clen%2Cdur%2Cgir%2Cid%2Cip%2Cipbits%2Citag%2Clmt%2Crequiressl%2Csource%2Cupn%2Cexpire&key=yt5&itag=133&source=youtube&ms=au&fexp=931945%2C937417%2C913434%2C936916%2C934022%2C936923&mws=yes&ip=18.111.47.22&expire=1397255826&upn=GvZMjhbNN_M&ipbits=0&dur=576.300&requiressl=yes&mv=m&id=o-AOrBy4nOUh9_ykTNecZuCOtqwZEhyc23uMWiMM8L8xdt&sver=3&clen=5633674&gir=yes&lmt=1379262892362745&mt=1397234678&signature=7542439230F21ACABF55C3A5DF8DF6740A2BC6DA.311E42A416AD05D3E702E19535C4D0C40B7052C2&ratebypass=yes", "preference": -40, "height": 240, "player_url": "//s.ytimg.com/yts/jsbin/html5player-en_US-vflS6PgfC.js", "format_id": "133", "format_note": "DASH video", "format": "133 - 240p (DASH video)"}, {"ext": "3gp", "height": 144, "player_url": "//s.ytimg.com/yts/jsbin/html5player-en_US-vflS6PgfC.js", "width": 176, "format_id": "17", "url": "https://r3---sn-a8au-cvne.googlevideo.com/videoplayback?sparams=id%2Cip%2Cipbits%2Citag%2Crequiressl%2Csource%2Cupn%2Cexpire&key=yt5&itag=17&ip=18.111.47.22&ms=au&fexp=931945%2C937417%2C913434%2C936916%2C934022%2C936923&mws=yes&source=youtube&expire=1397255826&upn=QKdRqWlIbcQ&ipbits=0&requiressl=yes&mv=m&id=o-AOrBy4nOUh9_ykTNecZuCOtqwZEhyc23uMWiMM8L8xdt&sver=3&mt=1397234678&signature=4341DB5ABCD545D466C177C6BDC5AF3422C4A215.B825C04588D7E157E306451440D89B21FA983108&ratebypass=yes", "format": "17 - 176x144"}, {"ext": "3gp", "height": 240, "player_url": "//s.ytimg.com/yts/jsbin/html5player-en_US-vflS6PgfC.js", "width": 320, "format_id": "36", "url": "https://r3---sn-a8au-cvne.googlevideo.com/videoplayback?sparams=id%2Cip%2Cipbits%2Citag%2Crequiressl%2Csource%2Cupn%2Cexpire&key=yt5&itag=36&ip=18.111.47.22&ms=au&fexp=931945%2C937417%2C913434%2C936916%2C934022%2C936923&mws=yes&source=youtube&expire=1397255826&upn=QKdRqWlIbcQ&ipbits=0&requiressl=yes&mv=m&id=o-AOrBy4nOUh9_ykTNecZuCOtqwZEhyc23uMWiMM8L8xdt&sver=3&mt=1397234678&signature=1C50B6408B89348B98AEF6C9F758C4A2616F3647.3796593864ABF9B965C047D7DADAF82D74735503&ratebypass=yes", "format": "36 - 320x240"}, {"ext": "flv", "height": 240, "player_url": "//s.ytimg.com/yts/jsbin/html5player-en_US-vflS6PgfC.js", "width": 400, "format_id": "5", "url": "https://r3---sn-a8au-cvne.googlevideo.com/videoplayback?sparams=id%2Cip%2Cipbits%2Citag%2Crequiressl%2Csource%2Cupn%2Cexpire&key=yt5&itag=5&ip=18.111.47.22&ms=au&fexp=931945%2C937417%2C913434%2C936916%2C934022%2C936923&mws=yes&source=youtube&expire=1397255826&upn=QKdRqWlIbcQ&ipbits=0&requiressl=yes&mv=m&id=o-AOrBy4nOUh9_ykTNecZuCOtqwZEhyc23uMWiMM8L8xdt&sver=3&mt=1397234678&signature=17D9300339494CCEC776AC56D689741F09E110C8.B108B16093DB98C5E336E39D4B9CFF90168E26CF&ratebypass=yes", "format": "5 - 400x240"}, {"ext": "mp4", "height": 360, "player_url": "//s.ytimg.com/yts/jsbin/html5player-en_US-vflS6PgfC.js", "width": 640, "format_id": "18", "url": "https://r3---sn-a8au-cvne.googlevideo.com/videoplayback?sparams=id%2Cip%2Cipbits%2Citag%2Cratebypass%2Crequiressl%2Csource%2Cupn%2Cexpire&key=yt5&itag=18&source=youtube&ms=au&fexp=931945%2C937417%2C913434%2C936916%2C934022%2C936923&mws=yes&ip=18.111.47.22&expire=1397255826&ratebypass=yes&ipbits=0&requiressl=yes&mv=m&id=o-AOrBy4nOUh9_ykTNecZuCOtqwZEhyc23uMWiMM8L8xdt&sver=3&upn=QKdRqWlIbcQ&mt=1397234678&signature=84348B07D658EAFE81AB91DD2CBA2BFDE2567568.B17FC8CCFEE4579E5FFB6A474453445019CC86A0", "format": "18 - 640x360"}], "url": "https://r3---sn-a8au-cvne.googlevideo.com/videoplayback?sparams=id%2Cip%2Cipbits%2Citag%2Cratebypass%2Crequiressl%2Csource%2Cupn%2Cexpire&key=yt5&itag=18&source=youtube&ms=au&fexp=931945%2C937417%2C913434%2C936916%2C934022%2C936923&mws=yes&ip=18.111.47.22&expire=1397255826&ratebypass=yes&ipbits=0&requiressl=yes&mv=m&id=o-AOrBy4nOUh9_ykTNecZuCOtqwZEhyc23uMWiMM8L8xdt&sver=3&upn=QKdRqWlIbcQ&mt=1397234678&signature=84348B07D658EAFE81AB91DD2CBA2BFDE2567568.B17FC8CCFEE4579E5FFB6A474453445019CC86A0", "id": "HPZHmtyT0uo", "fulltitle": "Marilyn Manson And The Spooky Kids - Herpes [coke and sodomy version]", "height": 360, "view_count": 1739, "upload_date": "20100822", "width": 640, "thumbnail": "https://i1.ytimg.com/vi/HPZHmtyT0uo/hqdefault.jpg", "dislike_count": 1, "format_id": "18", "uploader_id": "purgatory47", "uploader": "purgatory47", "ext": "mp4", "extractor": "youtube", "playlist": null, "like_count": 21, "description": "off the coke and sodomy album", "webpage_url_basename": "watch", "webpage_url": "https://www.youtube.com/watch?v=HPZHmtyT0uo", "playlist_index": null, "duration": 577, "age_limit": 0, "annotations": null, "display_id": "HPZHmtyT0uo", "player_url": "//s.ytimg.com/yts/jsbin/html5player-en_US-vflS6PgfC.js", "subtitles": null, "title": "Marilyn Manson And The Spooky Kids - Herpes [coke and sodomy version]"}